anosys_sdk_core/__init__.py
anosys_sdk_core/client.py
anosys_sdk_core/config.py
anosys_sdk_core/context.py
anosys_sdk_core/decorators.py
anosys_sdk_core/models.py
anosys_sdk_core/raw_logger.py
anosys_sdk_core/redaction.py
anosys_sdk_core/util/__init__.py
anosys_sdk_core/util/batching.py
anosys_sdk_core/util/json.py
anosys_sdk_core-1.0.1.dist-info/METADATA
anosys_sdk_core-1.0.1.dist-info/WHEEL
anosys_sdk_core-1.0.1.dist-info/top_level.txt
anosys_sdk_core-1.0.1.dist-info/RECORD
