Metadata-Version: 2.4
Name: anosys-sdk-core
Version: 1.0.1
Summary: Core utilities for AnoSys SDK - AI observability and monitoring
Author-email: AnoSys <support@anosys.ai>
Project-URL: Homepage, https://anosys.ai
Project-URL: Documentation, https://docs.anosys.ai
Project-URL: Repository, https://github.com/anosys-ai/anosys-sdk
Keywords: anosys,observability,monitoring,logging,ai,llm
Classifier: Development Status :: 4 - Beta
Classifier: Intended Audience :: Developers
Classifier: License :: OSI Approved :: Apache Software License
Classifier: Programming Language :: Python :: 3
Classifier: Programming Language :: Python :: 3.10
Classifier: Programming Language :: Python :: 3.11
Classifier: Programming Language :: Python :: 3.12
Classifier: Topic :: Software Development :: Libraries :: Python Modules
Classifier: Topic :: System :: Monitoring
Requires-Python: >=3.10
Requires-Dist: requests>=2.25.1
Requires-Dist: python-dotenv>=0.21.0
